syncpool_py/__init__.py
syncpool_py/exceptions.py
syncpool_py/objects.py
syncpool_py/pools/__init__.py
syncpool_py/pools/asyncpool.py
syncpool_py/pools/syncpool.py
syncpool_py-0.1.1.dist-info/LICENSE
syncpool_py-0.1.1.dist-info/METADATA
syncpool_py-0.1.1.dist-info/WHEEL
syncpool_py-0.1.1.dist-info/top_level.txt
syncpool_py-0.1.1.dist-info/RECORD
