Metadata-Version: 2.1
Name: syncpool-py
Version: 0.1.1
Summary: Synchronization object-pools, imitating Go's (Golang) sync.Pool implementation.
Home-page: https://github.com/AGitmit/syncpool
Author: Amit Nakash
License-File: LICENSE
